{
  "title": "queueMicroTask in JavaScript\r",
  "published": false,
  "featured": false,
  "component": false,
  "toc": true,
  "body": {
    "raw": "\r\nIn this article, we analyze queueMicroTask function in [React source code](https://github.com/facebook/react/blob/5d19e1c8d1a6c0b5cd7532d43b707191eaf105b7/packages/react/src/ReactAct.js#L361)  \r\nReact uses queueMicroTask in a file named ReactAct.js. This is a [public API, act](https://react.dev/reference/react/act).\r\n\r\nact is a test helper to apply pending React updates before making assertions.\r\n\r\n```plaintext\r\nawait act(async actFn)\r\n```\r\n\r\n[ReactAct.js](https://github.com/facebook/react/blob/5d19e1c8d1a6c0b5cd7532d43b707191eaf105b7/packages/react/src/ReactAct.js#L361) has a lot of code, let’s narrow down our focus on to queueMicroTask.\r\n\r\n# **Where is queueMicroTask called in ReactAct.js?**\r\n\r\n![](https://miro.medium.com/v2/resize:fit:875/1*PlQpveiCXPPH8TMk27pXvQ.png)\r\n\r\n`queueSeveralMicrotasks` is found at the end of this ReactAct.js file and calls queueMicroTask with a callback and has detailed comment explaining its purpose.\r\n\r\nqueueSeveralMicrotasks is found to be called in two places:\r\n\r\n* [https://github.com/facebook/react/blob/5d19e1c8d1a6c0b5cd7532d43b707191eaf105b7/packages/react/src/ReactAct.js#L121](https://github.com/facebook/react/blob/5d19e1c8d1a6c0b5cd7532d43b707191eaf105b7/packages/react/src/ReactAct.js#L121)\r\n    \r\n\r\n```plaintext\r\n// Warn if the an `act` call with an async scope is not awaited. In a\r\n // future release, consider making this an error.\r\n queueSeveralMicrotasks(() => {\r\n   if (!didAwaitActCall && !didWarnNoAwaitAct) {\r\n     didWarnNoAwaitAct = true;\r\n     console.error(\r\n       'You called act(async () => …) without await. ' +\r\n       'This could lead to unexpected testing behaviour, ' +\r\n       'interleaving multiple act calls and mixing their ' +\r\n       'scopes. ' +\r\n       'You should - await act(async () => …);',\r\n     );\r\n   }\r\n });\r\n```\r\n\r\n* [https://github.com/facebook/react/blob/5d19e1c8d1a6c0b5cd7532d43b707191eaf105b7/packages/react/src/ReactAct.js#L196](https://github.com/facebook/react/blob/5d19e1c8d1a6c0b5cd7532d43b707191eaf105b7/packages/react/src/ReactAct.js#L196)\r\n    \r\n\r\n```plaintext\r\n// Warn if something suspends but the `act` call is not awaited.\r\n// In a future release, consider making this an error.\r\nif (queue.length !== 0) {\r\n queueSeveralMicrotasks(() => {\r\n if (!didAwaitActCall && !didWarnNoAwaitAct) {\r\n   didWarnNoAwaitAct = true;\r\n   console.error(\r\n     'A component suspended inside an `act` scope, but the ' +\r\n     '`act` call was not awaited. When testing React ' +\r\n     'components that depend on asynchronous data, you must ' +\r\n     'await the result:\\n\\n' +\r\n     'await act(() => …)',\r\n   );\r\n   }\r\n });\r\n}\r\n```\r\n\r\nNow that we saw how queueMicroTask is used, let’s now understand the definition of queueMicroTask.\r\n\r\n# **queueMicroTask**\r\n\r\nThe queueMicrotask() method of the Window interface queues a microtask to be executed at a safe time prior to control returning to the browser’s event loop.\r\n\r\nThe microtask is a short function which will run after the current task has completed its work and when there is no other code waiting to be run before control of the execution context is returned to the browser’s event loop.\r\n\r\nThis lets your code run without interfering with any other, potentially higher priority, code that is pending, but before the browser regains control over the execution context, potentially depending on work you need to complete.\r\n\r\nRead more about queueMicroTask at [MDN Docs](https://developer.mozilla.org/en-US/docs/Web/API/Window/queueMicrotask).\r\n\r\n## **Example:**\r\n\r\nHere’s an example of how microtasks and macrotasks interact with the browser’s execution:\r\n\r\n```plaintext\r\nconsole.log('Synchronous 1'); // 1\r\nPromise.resolve().then(() => {\r\n console.log('Microtask 1'); // 3\r\n});\r\nconsole.log('Synchronous 2'); // 2\r\nsetTimeout(() => {\r\n console.log('Macrotask 1'); // 5\r\n}, 0);\r\nconsole.log('Synchronous 3'); // 4\r\n```\r\n\r\n## **Breakdown:**\r\n\r\nThe synchronous code runs first, outputting:  \r\n‘Synchronous 1’  \r\n‘Synchronous 2’  \r\n‘Synchronous 3’\r\n\r\nBefore the browser gets a chance to handle any pending rendering or macrotasks, the microtask queue is processed:\r\n\r\nThe Promise.resolve().then(…) callback is added to the microtask queue and is executed right after the synchronous code block is finished, logging:  \r\n‘Microtask 1’\r\n\r\nAfter the microtask queue is emptied, the browser regains control and can:\r\n\r\nRun macrotasks, like the setTimeout callback, which logs:\r\n\r\n‘Macrotask 1’\r\n\r\n## **Final output**\r\n\r\n```plaintext\r\nSynchronous 1\r\nSynchronous 2\r\nSynchronous 3\r\nMicrotask 1\r\nMacrotask 1\r\n```\r\n\r\n# **About me:**\r\n\r\nHey, my name is Ramu Narasinga. I study large open-source projects and create content about their codebase architecture and best practices, sharing it through articles, videos.\r\n\r\nI am open to work on interesting projects. Send me an email at ramu.narasinga@gmail.com\r\n\r\nMy Github — [https://github.com/ramu-narasinga](https://github.com/ramu-narasinga)\r\n\r\nMy website — [https://ramunarasinga.com](https://ramunarasinga.com/)\r\n\r\nMy Youtube channel — [https://www.youtube.com/@thinkthroo](https://www.youtube.com/@thinkthroo)\r\n\r\nLearning platform — [https://thinkthroo.com](https://thinkthroo.com/)\r\n\r\nCodebase Architecture — [https://app.thinkthroo.com/architecture](https://app.thinkthroo.com/architecture)\r\n\r\nBest practices — [https://app.thinkthroo.com/best-practices](https://app.thinkthroo.com/best-practices)\r\n\r\nProduction-grade projects — [https://app.thinkthroo.com/production-grade-projects](https://app.thinkthroo.com/production-grade-projects)\r\n\r\n# **References:**\r\n\r\n1. [https://developer.mozilla.org/en-US/docs/Web/API/Window/queueMicrotask](https://developer.mozilla.org/en-US/docs/Web/API/Window/queueMicrotask)\r\n    \r\n2. [https://github.com/facebook/react/blob/5d19e1c8d1a6c0b5cd7532d43b707191eaf105b7/packages/react/src/ReactAct.js#L361](https://github.com/facebook/react/blob/5d19e1c8d1a6c0b5cd7532d43b707191eaf105b7/packages/react/src/ReactAct.js#L361)\r\n    \r\n3. [https://developer.mozilla.org/en-US/docs/Web/API/HTML\\_DOM\\_API/Microtask\\_guide](https://developer.mozilla.org/en-US/docs/Web/API/HTML_DOM_API/Microtask_guide)\r\n    \r\n4. [https://react.dev/reference/react/act](https://react.dev/reference/react/act)\r\n    \r\n5. [https://javascript.info/event-loop](https://javascript.info/event-loop)\r\n    \r\n\r\n[  \r\n](https://medium.com/tag/javascript?source=post_page-----b8796f5562e1--------------------------------)\r\n",
    "code": "var Component=(()=>{var p=Object.create;var r=Object.defineProperty;var u=Object.getOwnPropertyDescriptor;var m=Object.getOwnPropertyNames;var g=Object.getPrototypeOf,b=Object.prototype.hasOwnProperty;var f=(a,e)=>()=>(e||a((e={exports:{}}).exports,e),e.exports),k=(a,e)=>{for(var c in e)r(a,c,{get:e[c],enumerable:!0})},s=(a,e,c,i)=>{if(e&&typeof e==\"object\"||typeof e==\"function\")for(let t of m(e))!b.call(a,t)&&t!==c&&r(a,t,{get:()=>e[t],enumerable:!(i=u(e,t))||i.enumerable});return a};var w=(a,e,c)=>(c=a!=null?p(g(a)):{},s(e||!a||!a.__esModule?r(c,\"default\",{value:a,enumerable:!0}):c,a)),N=a=>s(r({},\"__esModule\",{value:!0}),a);var d=f((A,l)=>{l.exports=_jsx_runtime});var M={};k(M,{default:()=>h,frontmatter:()=>y});var n=w(d()),y={title:\"queueMicroTask in JavaScript\"};function o(a){let e={a:\"a\",br:\"br\",code:\"code\",div:\"div\",h1:\"h1\",h2:\"h2\",img:\"img\",li:\"li\",ol:\"ol\",p:\"p\",pre:\"pre\",span:\"span\",strong:\"strong\",ul:\"ul\",...a.components};return(0,n.jsxs)(n.Fragment,{children:[(0,n.jsxs)(e.p,{children:[\"In this article, we analyze queueMicroTask function in \",(0,n.jsx)(e.a,{href:\"https://github.com/facebook/react/blob/5d19e1c8d1a6c0b5cd7532d43b707191eaf105b7/packages/react/src/ReactAct.js#L361\",children:\"React source code\"}),(0,n.jsx)(e.br,{}),`\n`,\"React uses queueMicroTask in a file named ReactAct.js. This is a \",(0,n.jsx)(e.a,{href:\"https://react.dev/reference/react/act\",children:\"public API, act\"}),\".\"]}),`\n`,(0,n.jsx)(e.p,{children:\"act is a test helper to apply pending React updates before making assertions.\"}),`\n`,(0,n.jsx)(e.div,{\"data-rehype-pretty-code-fragment\":\"\",children:(0,n.jsx)(e.pre,{\"data-language\":\"plaintext\",\"data-theme\":\"default\",children:(0,n.jsx)(e.code,{\"data-language\":\"plaintext\",\"data-theme\":\"default\",children:(0,n.jsx)(e.span,{className:\"line\",children:(0,n.jsx)(e.span,{children:\"await act(async actFn)\"})})})})}),`\n`,(0,n.jsxs)(e.p,{children:[(0,n.jsx)(e.a,{href:\"https://github.com/facebook/react/blob/5d19e1c8d1a6c0b5cd7532d43b707191eaf105b7/packages/react/src/ReactAct.js#L361\",children:\"ReactAct.js\"}),\" has a lot of code, let\\u2019s narrow down our focus on to queueMicroTask.\"]}),`\n`,(0,n.jsx)(e.h1,{id:\"where-is-queuemicrotask-called-in-reactactjs\",children:(0,n.jsx)(e.strong,{children:\"Where is queueMicroTask called in ReactAct.js?\"})}),`\n`,(0,n.jsx)(e.p,{children:(0,n.jsx)(e.img,{src:\"https://miro.medium.com/v2/resize:fit:875/1*PlQpveiCXPPH8TMk27pXvQ.png\",alt:\"\"})}),`\n`,(0,n.jsxs)(e.p,{children:[(0,n.jsx)(e.code,{children:\"queueSeveralMicrotasks\"}),\" is found at the end of this ReactAct.js file and calls queueMicroTask with a callback and has detailed comment explaining its purpose.\"]}),`\n`,(0,n.jsx)(e.p,{children:\"queueSeveralMicrotasks is found to be called in two places:\"}),`\n`,(0,n.jsxs)(e.ul,{children:[`\n`,(0,n.jsx)(e.li,{children:(0,n.jsx)(e.a,{href:\"https://github.com/facebook/react/blob/5d19e1c8d1a6c0b5cd7532d43b707191eaf105b7/packages/react/src/ReactAct.js#L121\",children:\"https://github.com/facebook/react/blob/5d19e1c8d1a6c0b5cd7532d43b707191eaf105b7/packages/react/src/ReactAct.js#L121\"})}),`\n`]}),`\n`,(0,n.jsx)(e.div,{\"data-rehype-pretty-code-fragment\":\"\",children:(0,n.jsx)(e.pre,{\"data-language\":\"plaintext\",\"data-theme\":\"default\",children:(0,n.jsxs)(e.code,{\"data-language\":\"plaintext\",\"data-theme\":\"default\",children:[(0,n.jsx)(e.span,{className:\"line\",children:(0,n.jsx)(e.span,{children:\"// Warn if the an `act` call with an async scope is not awaited. In a\"})}),`\n`,(0,n.jsx)(e.span,{className:\"line\",children:(0,n.jsx)(e.span,{children:\" // future release, consider making this an error.\"})}),`\n`,(0,n.jsx)(e.span,{className:\"line\",children:(0,n.jsx)(e.span,{children:\" queueSeveralMicrotasks(() => {\"})}),`\n`,(0,n.jsx)(e.span,{className:\"line\",children:(0,n.jsx)(e.span,{children:\"   if (!didAwaitActCall && !didWarnNoAwaitAct) {\"})}),`\n`,(0,n.jsx)(e.span,{className:\"line\",children:(0,n.jsx)(e.span,{children:\"     didWarnNoAwaitAct = true;\"})}),`\n`,(0,n.jsx)(e.span,{className:\"line\",children:(0,n.jsx)(e.span,{children:\"     console.error(\"})}),`\n`,(0,n.jsx)(e.span,{className:\"line\",children:(0,n.jsx)(e.span,{children:\"       'You called act(async () => \\u2026) without await. ' +\"})}),`\n`,(0,n.jsx)(e.span,{className:\"line\",children:(0,n.jsx)(e.span,{children:\"       'This could lead to unexpected testing behaviour, ' +\"})}),`\n`,(0,n.jsx)(e.span,{className:\"line\",children:(0,n.jsx)(e.span,{children:\"       'interleaving multiple act calls and mixing their ' +\"})}),`\n`,(0,n.jsx)(e.span,{className:\"line\",children:(0,n.jsx)(e.span,{children:\"       'scopes. ' +\"})}),`\n`,(0,n.jsx)(e.span,{className:\"line\",children:(0,n.jsx)(e.span,{children:\"       'You should - await act(async () => \\u2026);',\"})}),`\n`,(0,n.jsx)(e.span,{className:\"line\",children:(0,n.jsx)(e.span,{children:\"     );\"})}),`\n`,(0,n.jsx)(e.span,{className:\"line\",children:(0,n.jsx)(e.span,{children:\"   }\"})}),`\n`,(0,n.jsx)(e.span,{className:\"line\",children:(0,n.jsx)(e.span,{children:\" });\"})})]})})}),`\n`,(0,n.jsxs)(e.ul,{children:[`\n`,(0,n.jsx)(e.li,{children:(0,n.jsx)(e.a,{href:\"https://github.com/facebook/react/blob/5d19e1c8d1a6c0b5cd7532d43b707191eaf105b7/packages/react/src/ReactAct.js#L196\",children:\"https://github.com/facebook/react/blob/5d19e1c8d1a6c0b5cd7532d43b707191eaf105b7/packages/react/src/ReactAct.js#L196\"})}),`\n`]}),`\n`,(0,n.jsx)(e.div,{\"data-rehype-pretty-code-fragment\":\"\",children:(0,n.jsx)(e.pre,{\"data-language\":\"plaintext\",\"data-theme\":\"default\",children:(0,n.jsxs)(e.code,{\"data-language\":\"plaintext\",\"data-theme\":\"default\",children:[(0,n.jsx)(e.span,{className:\"line\",children:(0,n.jsx)(e.span,{children:\"// Warn if something suspends but the `act` call is not awaited.\"})}),`\n`,(0,n.jsx)(e.span,{className:\"line\",children:(0,n.jsx)(e.span,{children:\"// In a future release, consider making this an error.\"})}),`\n`,(0,n.jsx)(e.span,{className:\"line\",children:(0,n.jsx)(e.span,{children:\"if (queue.length !== 0) {\"})}),`\n`,(0,n.jsx)(e.span,{className:\"line\",children:(0,n.jsx)(e.span,{children:\" queueSeveralMicrotasks(() => {\"})}),`\n`,(0,n.jsx)(e.span,{className:\"line\",children:(0,n.jsx)(e.span,{children:\" if (!didAwaitActCall && !didWarnNoAwaitAct) {\"})}),`\n`,(0,n.jsx)(e.span,{className:\"line\",children:(0,n.jsx)(e.span,{children:\"   didWarnNoAwaitAct = true;\"})}),`\n`,(0,n.jsx)(e.span,{className:\"line\",children:(0,n.jsx)(e.span,{children:\"   console.error(\"})}),`\n`,(0,n.jsx)(e.span,{className:\"line\",children:(0,n.jsx)(e.span,{children:\"     'A component suspended inside an `act` scope, but the ' +\"})}),`\n`,(0,n.jsx)(e.span,{className:\"line\",children:(0,n.jsx)(e.span,{children:\"     '`act` call was not awaited. When testing React ' +\"})}),`\n`,(0,n.jsx)(e.span,{className:\"line\",children:(0,n.jsx)(e.span,{children:\"     'components that depend on asynchronous data, you must ' +\"})}),`\n`,(0,n.jsx)(e.span,{className:\"line\",children:(0,n.jsx)(e.span,{children:\"     'await the result:\\\\n\\\\n' +\"})}),`\n`,(0,n.jsx)(e.span,{className:\"line\",children:(0,n.jsx)(e.span,{children:\"     'await act(() => \\u2026)',\"})}),`\n`,(0,n.jsx)(e.span,{className:\"line\",children:(0,n.jsx)(e.span,{children:\"   );\"})}),`\n`,(0,n.jsx)(e.span,{className:\"line\",children:(0,n.jsx)(e.span,{children:\"   }\"})}),`\n`,(0,n.jsx)(e.span,{className:\"line\",children:(0,n.jsx)(e.span,{children:\" });\"})}),`\n`,(0,n.jsx)(e.span,{className:\"line\",children:(0,n.jsx)(e.span,{children:\"}\"})})]})})}),`\n`,(0,n.jsx)(e.p,{children:\"Now that we saw how queueMicroTask is used, let\\u2019s now understand the definition of queueMicroTask.\"}),`\n`,(0,n.jsx)(e.h1,{id:\"queuemicrotask\",children:(0,n.jsx)(e.strong,{children:\"queueMicroTask\"})}),`\n`,(0,n.jsx)(e.p,{children:\"The queueMicrotask() method of the Window interface queues a microtask to be executed at a safe time prior to control returning to the browser\\u2019s event loop.\"}),`\n`,(0,n.jsx)(e.p,{children:\"The microtask is a short function which will run after the current task has completed its work and when there is no other code waiting to be run before control of the execution context is returned to the browser\\u2019s event loop.\"}),`\n`,(0,n.jsx)(e.p,{children:\"This lets your code run without interfering with any other, potentially higher priority, code that is pending, but before the browser regains control over the execution context, potentially depending on work you need to complete.\"}),`\n`,(0,n.jsxs)(e.p,{children:[\"Read more about queueMicroTask at \",(0,n.jsx)(e.a,{href:\"https://developer.mozilla.org/en-US/docs/Web/API/Window/queueMicrotask\",children:\"MDN Docs\"}),\".\"]}),`\n`,(0,n.jsx)(e.h2,{id:\"example\",children:(0,n.jsx)(e.strong,{children:\"Example:\"})}),`\n`,(0,n.jsx)(e.p,{children:\"Here\\u2019s an example of how microtasks and macrotasks interact with the browser\\u2019s execution:\"}),`\n`,(0,n.jsx)(e.div,{\"data-rehype-pretty-code-fragment\":\"\",children:(0,n.jsx)(e.pre,{\"data-language\":\"plaintext\",\"data-theme\":\"default\",children:(0,n.jsxs)(e.code,{\"data-language\":\"plaintext\",\"data-theme\":\"default\",children:[(0,n.jsx)(e.span,{className:\"line\",children:(0,n.jsx)(e.span,{children:\"console.log('Synchronous 1'); // 1\"})}),`\n`,(0,n.jsx)(e.span,{className:\"line\",children:(0,n.jsx)(e.span,{children:\"Promise.resolve().then(() => {\"})}),`\n`,(0,n.jsx)(e.span,{className:\"line\",children:(0,n.jsx)(e.span,{children:\" console.log('Microtask 1'); // 3\"})}),`\n`,(0,n.jsx)(e.span,{className:\"line\",children:(0,n.jsx)(e.span,{children:\"});\"})}),`\n`,(0,n.jsx)(e.span,{className:\"line\",children:(0,n.jsx)(e.span,{children:\"console.log('Synchronous 2'); // 2\"})}),`\n`,(0,n.jsx)(e.span,{className:\"line\",children:(0,n.jsx)(e.span,{children:\"setTimeout(() => {\"})}),`\n`,(0,n.jsx)(e.span,{className:\"line\",children:(0,n.jsx)(e.span,{children:\" console.log('Macrotask 1'); // 5\"})}),`\n`,(0,n.jsx)(e.span,{className:\"line\",children:(0,n.jsx)(e.span,{children:\"}, 0);\"})}),`\n`,(0,n.jsx)(e.span,{className:\"line\",children:(0,n.jsx)(e.span,{children:\"console.log('Synchronous 3'); // 4\"})})]})})}),`\n`,(0,n.jsx)(e.h2,{id:\"breakdown\",children:(0,n.jsx)(e.strong,{children:\"Breakdown:\"})}),`\n`,(0,n.jsxs)(e.p,{children:[\"The synchronous code runs first, outputting:\",(0,n.jsx)(e.br,{}),`\n`,\"\\u2018Synchronous 1\\u2019\",(0,n.jsx)(e.br,{}),`\n`,\"\\u2018Synchronous 2\\u2019\",(0,n.jsx)(e.br,{}),`\n`,\"\\u2018Synchronous 3\\u2019\"]}),`\n`,(0,n.jsx)(e.p,{children:\"Before the browser gets a chance to handle any pending rendering or macrotasks, the microtask queue is processed:\"}),`\n`,(0,n.jsxs)(e.p,{children:[\"The Promise.resolve().then(\\u2026) callback is added to the microtask queue and is executed right after the synchronous code block is finished, logging:\",(0,n.jsx)(e.br,{}),`\n`,\"\\u2018Microtask 1\\u2019\"]}),`\n`,(0,n.jsx)(e.p,{children:\"After the microtask queue is emptied, the browser regains control and can:\"}),`\n`,(0,n.jsx)(e.p,{children:\"Run macrotasks, like the setTimeout callback, which logs:\"}),`\n`,(0,n.jsx)(e.p,{children:\"\\u2018Macrotask 1\\u2019\"}),`\n`,(0,n.jsx)(e.h2,{id:\"final-output\",children:(0,n.jsx)(e.strong,{children:\"Final output\"})}),`\n`,(0,n.jsx)(e.div,{\"data-rehype-pretty-code-fragment\":\"\",children:(0,n.jsx)(e.pre,{\"data-language\":\"plaintext\",\"data-theme\":\"default\",children:(0,n.jsxs)(e.code,{\"data-language\":\"plaintext\",\"data-theme\":\"default\",children:[(0,n.jsx)(e.span,{className:\"line\",children:(0,n.jsx)(e.span,{children:\"Synchronous 1\"})}),`\n`,(0,n.jsx)(e.span,{className:\"line\",children:(0,n.jsx)(e.span,{children:\"Synchronous 2\"})}),`\n`,(0,n.jsx)(e.span,{className:\"line\",children:(0,n.jsx)(e.span,{children:\"Synchronous 3\"})}),`\n`,(0,n.jsx)(e.span,{className:\"line\",children:(0,n.jsx)(e.span,{children:\"Microtask 1\"})}),`\n`,(0,n.jsx)(e.span,{className:\"line\",children:(0,n.jsx)(e.span,{children:\"Macrotask 1\"})})]})})}),`\n`,(0,n.jsx)(e.h1,{id:\"about-me\",children:(0,n.jsx)(e.strong,{children:\"About me:\"})}),`\n`,(0,n.jsx)(e.p,{children:\"Hey, my name is Ramu Narasinga. I study large open-source projects and create content about their codebase architecture and best practices, sharing it through articles, videos.\"}),`\n`,(0,n.jsxs)(e.p,{children:[\"I am open to work on interesting projects. Send me an email at \",(0,n.jsx)(e.a,{href:\"mailto:ramu.narasinga@gmail.com\",children:\"ramu.narasinga@gmail.com\"})]}),`\n`,(0,n.jsxs)(e.p,{children:[\"My Github \\u2014 \",(0,n.jsx)(e.a,{href:\"https://github.com/ramu-narasinga\",children:\"https://github.com/ramu-narasinga\"})]}),`\n`,(0,n.jsxs)(e.p,{children:[\"My website \\u2014 \",(0,n.jsx)(e.a,{href:\"https://ramunarasinga.com/\",children:\"https://ramunarasinga.com\"})]}),`\n`,(0,n.jsxs)(e.p,{children:[\"My Youtube channel \\u2014 \",(0,n.jsx)(e.a,{href:\"https://www.youtube.com/@thinkthroo\",children:\"https://www.youtube.com/@thinkthroo\"})]}),`\n`,(0,n.jsxs)(e.p,{children:[\"Learning platform \\u2014 \",(0,n.jsx)(e.a,{href:\"https://thinkthroo.com/\",children:\"https://thinkthroo.com\"})]}),`\n`,(0,n.jsxs)(e.p,{children:[\"Codebase Architecture \\u2014 \",(0,n.jsx)(e.a,{href:\"https://app.thinkthroo.com/architecture\",children:\"https://app.thinkthroo.com/architecture\"})]}),`\n`,(0,n.jsxs)(e.p,{children:[\"Best practices \\u2014 \",(0,n.jsx)(e.a,{href:\"https://app.thinkthroo.com/best-practices\",children:\"https://app.thinkthroo.com/best-practices\"})]}),`\n`,(0,n.jsxs)(e.p,{children:[\"Production-grade projects \\u2014 \",(0,n.jsx)(e.a,{href:\"https://app.thinkthroo.com/production-grade-projects\",children:\"https://app.thinkthroo.com/production-grade-projects\"})]}),`\n`,(0,n.jsx)(e.h1,{id:\"references\",children:(0,n.jsx)(e.strong,{children:\"References:\"})}),`\n`,(0,n.jsxs)(e.ol,{children:[`\n`,(0,n.jsxs)(e.li,{children:[`\n`,(0,n.jsx)(e.p,{children:(0,n.jsx)(e.a,{href:\"https://developer.mozilla.org/en-US/docs/Web/API/Window/queueMicrotask\",children:\"https://developer.mozilla.org/en-US/docs/Web/API/Window/queueMicrotask\"})}),`\n`]}),`\n`,(0,n.jsxs)(e.li,{children:[`\n`,(0,n.jsx)(e.p,{children:(0,n.jsx)(e.a,{href:\"https://github.com/facebook/react/blob/5d19e1c8d1a6c0b5cd7532d43b707191eaf105b7/packages/react/src/ReactAct.js#L361\",children:\"https://github.com/facebook/react/blob/5d19e1c8d1a6c0b5cd7532d43b707191eaf105b7/packages/react/src/ReactAct.js#L361\"})}),`\n`]}),`\n`,(0,n.jsxs)(e.li,{children:[`\n`,(0,n.jsx)(e.p,{children:(0,n.jsx)(e.a,{href:\"https://developer.mozilla.org/en-US/docs/Web/API/HTML_DOM_API/Microtask_guide\",children:\"https://developer.mozilla.org/en-US/docs/Web/API/HTML_DOM_API/Microtask_guide\"})}),`\n`]}),`\n`,(0,n.jsxs)(e.li,{children:[`\n`,(0,n.jsx)(e.p,{children:(0,n.jsx)(e.a,{href:\"https://react.dev/reference/react/act\",children:\"https://react.dev/reference/react/act\"})}),`\n`]}),`\n`,(0,n.jsxs)(e.li,{children:[`\n`,(0,n.jsx)(e.p,{children:(0,n.jsx)(e.a,{href:\"https://javascript.info/event-loop\",children:\"https://javascript.info/event-loop\"})}),`\n`]}),`\n`]}),`\n`,(0,n.jsx)(e.p,{children:(0,n.jsxs)(e.a,{href:\"https://medium.com/tag/javascript?source=post_page-----b8796f5562e1--------------------------------\",children:[(0,n.jsx)(e.br,{}),`\n`]})})]})}function h(a={}){let{wrapper:e}=a.components||{};return e?(0,n.jsx)(e,{...a,children:(0,n.jsx)(o,{...a})}):o(a)}return N(M);})();\n;return Component;"
  },
  "_id": "blog/queueMicroTask-in-JavaScript.mdx",
  "_raw": {
    "sourceFilePath": "blog/queueMicroTask-in-JavaScript.mdx",
    "sourceFileName": "queueMicroTask-in-JavaScript.mdx",
    "sourceFileDir": "blog",
    "contentType": "mdx",
    "flattenedPath": "blog/queueMicroTask-in-JavaScript"
  },
  "type": "Doc",
  "slug": "/blog/queueMicroTask-in-JavaScript",
  "slugAsParams": "queueMicroTask-in-JavaScript"
}