{
  "title": "useSyncExternalStore usage in TipTap source code\r",
  "published": false,
  "featured": false,
  "component": false,
  "toc": true,
  "body": {
    "raw": "\r\nIn this article, we will review [useSyncExternalStore](https://react.dev/reference/react/useSyncExternalStore) usage in TipTap. \r\n\r\n![](https://cdn-images-1.medium.com/max/1600/1*SZu_B0RXKLINGiZeGAdeTw.png)\r\n\r\nI found `useSyncExternalStore` is used in 3 files:\r\n\r\n* [EditorContent.tsx](https://github.com/ueberdosis/tiptap/blob/4d9cc0519f7d4d3df69cd2d6839718a9ac92244c/packages/react/src/EditorContent.tsx#L32)\r\n    \r\n* [useEditorState.ts](https://github.com/ueberdosis/tiptap/blob/4d9cc0519f7d4d3df69cd2d6839718a9ac92244c/packages/react/src/useEditorState.ts#L162)\r\n    \r\n* [useEditor.ts](https://github.com/ueberdosis/tiptap/blob/4d9cc0519f7d4d3df69cd2d6839718a9ac92244c/packages/react/src/useEditor.ts#L345)\r\n    \r\n\r\nBefore we look at these files, let’s learn what is useSyncExternalStore.\r\n\r\n### useSyncExternalStore\r\n\r\n[`useSyncExternalStore`](https://react.dev/reference/react/useSyncExternalStore) is a React Hook that lets you subscribe to an external store.\r\n\r\nRead more about [useSyncExternalStore](https://react.dev/reference/react/useSyncExternalStore).\r\n\r\n```js\r\nconst snapshot = useSyncExternalStore(subscribe, getSnapshot, getServerSnapshot?)\r\n```\r\n\r\n### EditorContent.tsx\r\n\r\n```js\r\nimport { useSyncExternalStore } from 'use-sync-external-store/shim'\r\n...\r\n/**\r\n * This component renders all of the editor's node views.\r\n */\r\nconst Portals: React.FC<{ contentComponent: ContentComponent }> = ({\r\n  contentComponent,\r\n}) => {\r\n  // For performance reasons, we render the node view portals on state changes only\r\n  const renderers = useSyncExternalStore(\r\n    contentComponent.subscribe,\r\n    contentComponent.getSnapshot,\r\n    contentComponent.getServerSnapshot,\r\n  )\r\n\r\n  // This allows us to directly render the portals without any additional wrapper\r\n  return (\r\n    <>\r\n      {Object.values(renderers)}\r\n    </>\r\n  )\r\n}\r\n```\r\n\r\nPay attention to the comment in this above code snippet:\r\n\r\n> For performance reasons, we render the node view portals on state changes only\r\n\r\n### useEditorState.ts\r\n\r\n```js\r\nimport { useSyncExternalStoreWithSelector } from 'use-sync-external-store/shim/with-selector'\r\n...\r\n/**\r\n * This hook allows you to watch for changes on the editor instance.\r\n * It will allow you to select a part of the editor state and re-render the component when it changes.\r\n * @example\r\n * ```tsx\r\n * const editor = useEditor({...options})\r\n * const { currentSelection } = useEditorState({\r\n *  editor,\r\n *  selector: snapshot => ({ currentSelection: snapshot.editor.state.selection }),\r\n * })\r\n */\r\nexport function useEditorState<TSelectorResult>(\r\n  options: UseEditorStateOptions<TSelectorResult, Editor> | UseEditorStateOptions<TSelectorResult, Editor | null>,\r\n): TSelectorResult | null {\r\n  const [editorStateManager] = useState(() => new EditorStateManager(options.editor))\r\n\r\n  // Using the `useSyncExternalStore` hook to sync the editor instance with the component state\r\n  const selectedState = useSyncExternalStoreWithSelector(\r\n    editorStateManager.subscribe,\r\n    editorStateManager.getSnapshot,\r\n    editorStateManager.getServerSnapshot,\r\n    options.selector as UseEditorStateOptions<TSelectorResult, Editor | null>['selector'],\r\n    options.equalityFn ?? deepEqual,\r\n  )\r\n\r\n  useIsomorphicLayoutEffect(() => {\r\n    return editorStateManager.watch(options.editor)\r\n  }, [options.editor, editorStateManager])\r\n\r\n  useDebugValue(selectedState)\r\n\r\n  return selectedState\r\n}\r\n```\r\n\r\n> Using the `useSyncExternalStore` hook to sync the editor instance with the component state\r\n\r\nIn the `EditorContent.tsx`, the import was from `use-sync-external-store/shim` but here in this useEditorState, import is from `use-sync-external-store/shim/with-selector`.\r\n\r\n### useEditor.ts\r\n\r\n```js\r\nimport { useSyncExternalStore } from 'use-sync-external-store/shim'\r\n...\r\nexport function useEditor(\r\n  options: UseEditorOptions = {},\r\n  deps: DependencyList = [],\r\n): Editor | null {\r\n  const mostRecentOptions = useRef(options)\r\n\r\n  mostRecentOptions.current = options\r\n\r\n  const [instanceManager] = useState(() => new EditorInstanceManager(mostRecentOptions))\r\n\r\n  const editor = useSyncExternalStore(\r\n    instanceManager.subscribe,\r\n    instanceManager.getEditor,\r\n    instanceManager.getServerSnapshot,\r\n  )\r\n\r\n  useDebugValue(editor)\r\n```\r\n\r\nHere the external store is instanceManager.\r\n\r\n### About me:\r\n\r\nHey, my name is Ramu Narasinga. I study large open-source projects and create content about their codebase architecture and best practices, sharing it through articles, videos.\r\n\r\n***I am open to work on interesting projects. Send me an email at ramu.narasinga@gmail.com***\r\n\r\nMy Github — [https://github.com/ramu-narasinga](https://github.com/ramu-narasinga)\r\n\r\nMy website — [https://ramunarasinga.com](https://ramunarasinga.com/)\r\n\r\nMy Youtube channel — [https://www.youtube.com/@thinkthroo](https://www.youtube.com/@thinkthroo)\r\n\r\nLearning platform — [https://thinkthroo.com](https://thinkthroo.com/)\r\n\r\nCodebase Architecture — [https://app.thinkthroo.com/architecture](https://app.thinkthroo.com/architecture)\r\n\r\nBest practices — [https://app.thinkthroo.com/best-practices](https://app.thinkthroo.com/best-practices)\r\n\r\nProduction-grade projects — [https://app.thinkthroo.com/production-grade-projects](https://app.thinkthroo.com/production-grade-projects)\r\n\r\n### References:\r\n\r\n1. [useSyncExternalStore&type=code](https://github.com/search?q=repo%3Aueberdosis%2Ftiptap%20useSyncExternalStore&type=code)\r\n    \r\n2. [packages/react/src/EditorContent.tsx#L32](https://github.com/ueberdosis/tiptap/blob/4d9cc0519f7d4d3df69cd2d6839718a9ac92244c/packages/react/src/EditorContent.tsx#L32)\r\n    \r\n3. [packages/react/src/useEditorState.ts#L162](https://github.com/ueberdosis/tiptap/blob/4d9cc0519f7d4d3df69cd2d6839718a9ac92244c/packages/react/src/useEditorState.ts#L162)\r\n    \r\n4. [packages/react/src/useEditor.ts#L345](https://github.com/ueberdosis/tiptap/blob/4d9cc0519f7d4d3df69cd2d6839718a9ac92244c/packages/react/src/useEditor.ts#L345)\r\n    \r\n5. [https://react.dev/reference/react/useSyncExternalStore](https://react.dev/reference/react/useSyncExternalStore)",
    "code": "var Component=(()=>{var h=Object.create;var c=Object.defineProperty;var p=Object.getOwnPropertyDescriptor;var y=Object.getOwnPropertyNames;var m=Object.getPrototypeOf,u=Object.prototype.hasOwnProperty;var g=(l,e)=>()=>(e||l((e={exports:{}}).exports,e),e.exports),f=(l,e)=>{for(var s in e)c(l,s,{get:e[s],enumerable:!0})},t=(l,e,s,o)=>{if(e&&typeof e==\"object\"||typeof e==\"function\")for(let r of y(e))!u.call(l,r)&&r!==s&&c(l,r,{get:()=>e[r],enumerable:!(o=p(e,r))||o.enumerable});return l};var S=(l,e,s)=>(s=l!=null?h(m(l)):{},t(e||!l||!l.__esModule?c(s,\"default\",{value:l,enumerable:!0}):s,l)),b=l=>t(c({},\"__esModule\",{value:!0}),l);var F=g((w,a)=>{a.exports=_jsx_runtime});var E={};f(E,{default:()=>d,frontmatter:()=>N});var n=S(F()),N={title:\"useSyncExternalStore usage in TipTap source\\xA0code\"};function i(l){let e={a:\"a\",blockquote:\"blockquote\",code:\"code\",div:\"div\",em:\"em\",h3:\"h3\",img:\"img\",li:\"li\",ol:\"ol\",p:\"p\",pre:\"pre\",span:\"span\",strong:\"strong\",ul:\"ul\",...l.components};return(0,n.jsxs)(n.Fragment,{children:[(0,n.jsxs)(e.p,{children:[\"In this article, we will review \",(0,n.jsx)(e.a,{href:\"https://react.dev/reference/react/useSyncExternalStore\",children:\"useSyncExternalStore\"}),\" usage in TipTap.\\xA0\"]}),`\n`,(0,n.jsx)(e.p,{children:(0,n.jsx)(e.img,{src:\"https://cdn-images-1.medium.com/max/1600/1*SZu_B0RXKLINGiZeGAdeTw.png\",alt:\"\"})}),`\n`,(0,n.jsxs)(e.p,{children:[\"I found \",(0,n.jsx)(e.code,{children:\"useSyncExternalStore\"}),\" is used in 3 files:\"]}),`\n`,(0,n.jsxs)(e.ul,{children:[`\n`,(0,n.jsxs)(e.li,{children:[`\n`,(0,n.jsx)(e.p,{children:(0,n.jsx)(e.a,{href:\"https://github.com/ueberdosis/tiptap/blob/4d9cc0519f7d4d3df69cd2d6839718a9ac92244c/packages/react/src/EditorContent.tsx#L32\",children:\"EditorContent.tsx\"})}),`\n`]}),`\n`,(0,n.jsxs)(e.li,{children:[`\n`,(0,n.jsx)(e.p,{children:(0,n.jsx)(e.a,{href:\"https://github.com/ueberdosis/tiptap/blob/4d9cc0519f7d4d3df69cd2d6839718a9ac92244c/packages/react/src/useEditorState.ts#L162\",children:\"useEditorState.ts\"})}),`\n`]}),`\n`,(0,n.jsxs)(e.li,{children:[`\n`,(0,n.jsx)(e.p,{children:(0,n.jsx)(e.a,{href:\"https://github.com/ueberdosis/tiptap/blob/4d9cc0519f7d4d3df69cd2d6839718a9ac92244c/packages/react/src/useEditor.ts#L345\",children:\"useEditor.ts\"})}),`\n`]}),`\n`]}),`\n`,(0,n.jsx)(e.p,{children:\"Before we look at these files, let\\u2019s learn what is useSyncExternalStore.\"}),`\n`,(0,n.jsx)(e.h3,{id:\"usesyncexternalstore\",children:\"useSyncExternalStore\"}),`\n`,(0,n.jsxs)(e.p,{children:[(0,n.jsx)(e.a,{href:\"https://react.dev/reference/react/useSyncExternalStore\",children:(0,n.jsx)(e.code,{children:\"useSyncExternalStore\"})}),\" is a React Hook that lets you subscribe to an external store.\"]}),`\n`,(0,n.jsxs)(e.p,{children:[\"Read more about \",(0,n.jsx)(e.a,{href:\"https://react.dev/reference/react/useSyncExternalStore\",children:\"useSyncExternalStore\"}),\".\"]}),`\n`,(0,n.jsx)(e.div,{\"data-rehype-pretty-code-fragment\":\"\",children:(0,n.jsx)(e.pre,{\"data-language\":\"js\",\"data-theme\":\"default\",children:(0,n.jsx)(e.code,{\"data-language\":\"js\",\"data-theme\":\"default\",children:(0,n.jsxs)(e.span,{className:\"line\",children:[(0,n.jsx)(e.span,{style:{color:\"#FFF8\"},children:\"const\"}),(0,n.jsx)(e.span,{style:{color:\"#FFF\"},children:\" snapshot \"}),(0,n.jsx)(e.span,{style:{color:\"#FFF8\"},children:\"=\"}),(0,n.jsx)(e.span,{style:{color:\"#FFF\"},children:\" useSyncExternalStore\"}),(0,n.jsx)(e.span,{style:{color:\"#FFF8\"},children:\"(\"}),(0,n.jsx)(e.span,{style:{color:\"#FFF\"},children:\"subscribe\"}),(0,n.jsx)(e.span,{style:{color:\"#FFF8\"},children:\",\"}),(0,n.jsx)(e.span,{style:{color:\"#FFF\"},children:\" getSnapshot\"}),(0,n.jsx)(e.span,{style:{color:\"#FFF8\"},children:\",\"}),(0,n.jsx)(e.span,{style:{color:\"#FFF\"},children:\" getServerSnapshot\"}),(0,n.jsx)(e.span,{style:{color:\"#FFF8\"},children:\"?\"}),(0,n.jsx)(e.span,{style:{color:\"#FFF\"},children:\")\"})]})})})}),`\n`,(0,n.jsx)(e.h3,{id:\"editorcontenttsx\",children:\"EditorContent.tsx\"}),`\n`,(0,n.jsx)(e.div,{\"data-rehype-pretty-code-fragment\":\"\",children:(0,n.jsx)(e.pre,{\"data-language\":\"js\",\"data-theme\":\"default\",children:(0,n.jsxs)(e.code,{\"data-language\":\"js\",\"data-theme\":\"default\",children:[(0,n.jsxs)(e.span,{className:\"line\",children:[(0,n.jsx)(e.span,{style:{color:\"#FFF8\"},children:\"import\"}),(0,n.jsx)(e.span,{style:{color:\"#FFF8\"},children:\" {\"}),(0,n.jsx)(e.span,{style:{color:\"#FFF\"},children:\" useSyncExternalStore \"}),(0,n.jsx)(e.span,{style:{color:\"#FFF8\"},children:\"}\"}),(0,n.jsx)(e.span,{style:{color:\"#FFF8\"},children:\" from\"}),(0,n.jsx)(e.span,{style:{color:\"#FFF8\"},children:\" 'use-sync-external-store/shim'\"})]}),`\n`,(0,n.jsx)(e.span,{className:\"line\",children:(0,n.jsx)(e.span,{style:{color:\"#FFF8\"},children:\"...\"})}),`\n`,(0,n.jsx)(e.span,{className:\"line\",children:(0,n.jsx)(e.span,{style:{color:\"#FFF8\"},children:\"/**\"})}),`\n`,(0,n.jsx)(e.span,{className:\"line\",children:(0,n.jsx)(e.span,{style:{color:\"#FFF4\"},children:\" * This component renders all of the editor's node views.\"})}),`\n`,(0,n.jsx)(e.span,{className:\"line\",children:(0,n.jsx)(e.span,{style:{color:\"#FFF8\"},children:\" */\"})}),`\n`,(0,n.jsxs)(e.span,{className:\"line\",children:[(0,n.jsx)(e.span,{style:{color:\"#FFF8\"},children:\"const\"}),(0,n.jsx)(e.span,{style:{color:\"#FFF\",fontWeight:\"bold\"},children:\" Portals\"}),(0,n.jsx)(e.span,{style:{color:\"#FFF8\"},children:\":\"}),(0,n.jsx)(e.span,{style:{color:\"#FFF\",fontWeight:\"bold\"},children:\" React\"}),(0,n.jsx)(e.span,{style:{color:\"#FFF8\"},children:\".\"}),(0,n.jsx)(e.span,{style:{color:\"#FFF\",fontWeight:\"bold\"},children:\"FC\"}),(0,n.jsx)(e.span,{style:{color:\"#FFF8\"},children:\"<{\"}),(0,n.jsx)(e.span,{style:{color:\"#FFF\"},children:\" contentComponent\"}),(0,n.jsx)(e.span,{style:{color:\"#FFF8\"},children:\":\"}),(0,n.jsx)(e.span,{style:{color:\"#FFF\",fontWeight:\"bold\"},children:\" ContentComponent\"}),(0,n.jsx)(e.span,{style:{color:\"#FFF8\"},children:\" }>\"}),(0,n.jsx)(e.span,{style:{color:\"#FFF8\"},children:\" =\"}),(0,n.jsx)(e.span,{style:{color:\"#FFF8\"},children:\" ({\"})]}),`\n`,(0,n.jsxs)(e.span,{className:\"line\",children:[(0,n.jsx)(e.span,{style:{color:\"#FFF\"},children:\"  contentComponent\"}),(0,n.jsx)(e.span,{style:{color:\"#FFF8\"},children:\",\"})]}),`\n`,(0,n.jsxs)(e.span,{className:\"line\",children:[(0,n.jsx)(e.span,{style:{color:\"#FFF8\"},children:\"})\"}),(0,n.jsx)(e.span,{style:{color:\"#FFF8\"},children:\" =>\"}),(0,n.jsx)(e.span,{style:{color:\"#FFF8\"},children:\" {\"})]}),`\n`,(0,n.jsxs)(e.span,{className:\"line\",children:[(0,n.jsx)(e.span,{style:{color:\"#FFF8\"},children:\"  //\"}),(0,n.jsx)(e.span,{style:{color:\"#FFF4\"},children:\" For performance reasons, we render the node view portals on state changes only\"})]}),`\n`,(0,n.jsxs)(e.span,{className:\"line\",children:[(0,n.jsx)(e.span,{style:{color:\"#FFF8\"},children:\"  const\"}),(0,n.jsx)(e.span,{style:{color:\"#FFF\"},children:\" renderers \"}),(0,n.jsx)(e.span,{style:{color:\"#FFF8\"},children:\"=\"}),(0,n.jsx)(e.span,{style:{color:\"#FFF\"},children:\" useSyncExternalStore\"}),(0,n.jsx)(e.span,{style:{color:\"#FFF8\"},children:\"(\"})]}),`\n`,(0,n.jsxs)(e.span,{className:\"line\",children:[(0,n.jsx)(e.span,{style:{color:\"#FFF\"},children:\"    contentComponent\"}),(0,n.jsx)(e.span,{style:{color:\"#FFF8\"},children:\".\"}),(0,n.jsx)(e.span,{style:{color:\"#FFF\"},children:\"subscribe\"}),(0,n.jsx)(e.span,{style:{color:\"#FFF8\"},children:\",\"})]}),`\n`,(0,n.jsxs)(e.span,{className:\"line\",children:[(0,n.jsx)(e.span,{style:{color:\"#FFF\"},children:\"    contentComponent\"}),(0,n.jsx)(e.span,{style:{color:\"#FFF8\"},children:\".\"}),(0,n.jsx)(e.span,{style:{color:\"#FFF\"},children:\"getSnapshot\"}),(0,n.jsx)(e.span,{style:{color:\"#FFF8\"},children:\",\"})]}),`\n`,(0,n.jsxs)(e.span,{className:\"line\",children:[(0,n.jsx)(e.span,{style:{color:\"#FFF\"},children:\"    contentComponent\"}),(0,n.jsx)(e.span,{style:{color:\"#FFF8\"},children:\".\"}),(0,n.jsx)(e.span,{style:{color:\"#FFF\"},children:\"getServerSnapshot\"}),(0,n.jsx)(e.span,{style:{color:\"#FFF8\"},children:\",\"})]}),`\n`,(0,n.jsx)(e.span,{className:\"line\",children:(0,n.jsx)(e.span,{style:{color:\"#FFF8\"},children:\"  )\"})}),`\n`,(0,n.jsx)(e.span,{className:\"line\",children:\" \"}),`\n`,(0,n.jsxs)(e.span,{className:\"line\",children:[(0,n.jsx)(e.span,{style:{color:\"#FFF8\"},children:\"  //\"}),(0,n.jsx)(e.span,{style:{color:\"#FFF4\"},children:\" This allows us to directly render the portals without any additional wrapper\"})]}),`\n`,(0,n.jsxs)(e.span,{className:\"line\",children:[(0,n.jsx)(e.span,{style:{color:\"#FFF8\"},children:\"  return\"}),(0,n.jsx)(e.span,{style:{color:\"#FFF8\"},children:\" (\"})]}),`\n`,(0,n.jsx)(e.span,{className:\"line\",children:(0,n.jsx)(e.span,{style:{color:\"#FFF8\"},children:\"    <>\"})}),`\n`,(0,n.jsxs)(e.span,{className:\"line\",children:[(0,n.jsx)(e.span,{style:{color:\"#FFF8\"},children:\"      {\"}),(0,n.jsx)(e.span,{style:{color:\"#FFF\"},children:\"Object\"}),(0,n.jsx)(e.span,{style:{color:\"#FFF8\"},children:\".\"}),(0,n.jsx)(e.span,{style:{color:\"#FFF\"},children:\"values\"}),(0,n.jsx)(e.span,{style:{color:\"#FFF8\"},children:\"(\"}),(0,n.jsx)(e.span,{style:{color:\"#FFF\"},children:\"renderers\"}),(0,n.jsx)(e.span,{style:{color:\"#FFF8\"},children:\")}\"})]}),`\n`,(0,n.jsx)(e.span,{className:\"line\",children:(0,n.jsx)(e.span,{style:{color:\"#FFF8\"},children:\"    </>\"})}),`\n`,(0,n.jsx)(e.span,{className:\"line\",children:(0,n.jsx)(e.span,{style:{color:\"#FFF8\"},children:\"  )\"})}),`\n`,(0,n.jsx)(e.span,{className:\"line\",children:(0,n.jsx)(e.span,{style:{color:\"#FFF8\"},children:\"}\"})})]})})}),`\n`,(0,n.jsx)(e.p,{children:\"Pay attention to the comment in this above code snippet:\"}),`\n`,(0,n.jsxs)(e.blockquote,{children:[`\n`,(0,n.jsx)(e.p,{children:\"For performance reasons, we render the node view portals on state changes only\"}),`\n`]}),`\n`,(0,n.jsx)(e.h3,{id:\"useeditorstatets\",children:\"useEditorState.ts\"}),`\n`,(0,n.jsx)(e.div,{\"data-rehype-pretty-code-fragment\":\"\",children:(0,n.jsx)(e.pre,{\"data-language\":\"js\",\"data-theme\":\"default\",children:(0,n.jsxs)(e.code,{\"data-language\":\"js\",\"data-theme\":\"default\",children:[(0,n.jsxs)(e.span,{className:\"line\",children:[(0,n.jsx)(e.span,{style:{color:\"#FFF8\"},children:\"import\"}),(0,n.jsx)(e.span,{style:{color:\"#FFF8\"},children:\" {\"}),(0,n.jsx)(e.span,{style:{color:\"#FFF\"},children:\" useSyncExternalStoreWithSelector \"}),(0,n.jsx)(e.span,{style:{color:\"#FFF8\"},children:\"}\"}),(0,n.jsx)(e.span,{style:{color:\"#FFF8\"},children:\" from\"}),(0,n.jsx)(e.span,{style:{color:\"#FFF8\"},children:\" 'use-sync-external-store/shim/with-selector'\"})]}),`\n`,(0,n.jsx)(e.span,{className:\"line\",children:(0,n.jsx)(e.span,{style:{color:\"#FFF8\"},children:\"...\"})}),`\n`,(0,n.jsx)(e.span,{className:\"line\",children:(0,n.jsx)(e.span,{style:{color:\"#FFF8\"},children:\"/**\"})}),`\n`,(0,n.jsx)(e.span,{className:\"line\",children:(0,n.jsx)(e.span,{style:{color:\"#FFF4\"},children:\" * This hook allows you to watch for changes on the editor instance.\"})}),`\n`,(0,n.jsx)(e.span,{className:\"line\",children:(0,n.jsx)(e.span,{style:{color:\"#FFF4\"},children:\" * It will allow you to select a part of the editor state and re-render the component when it changes.\"})}),`\n`,(0,n.jsxs)(e.span,{className:\"line\",children:[(0,n.jsx)(e.span,{style:{color:\"#FFF4\"},children:\" * \"}),(0,n.jsx)(e.span,{style:{color:\"#FFF8\"},children:\"@example\"})]}),`\n`,(0,n.jsx)(e.span,{className:\"line\",children:(0,n.jsx)(e.span,{style:{color:\"#FFF4\"},children:\" * ```tsx\"})}),`\n`,(0,n.jsx)(e.span,{className:\"line\",children:(0,n.jsx)(e.span,{style:{color:\"#FFF4\"},children:\" * const editor = useEditor({...options})\"})}),`\n`,(0,n.jsx)(e.span,{className:\"line\",children:(0,n.jsx)(e.span,{style:{color:\"#FFF4\"},children:\" * const { currentSelection } = useEditorState({\"})}),`\n`,(0,n.jsx)(e.span,{className:\"line\",children:(0,n.jsx)(e.span,{style:{color:\"#FFF4\"},children:\" *  editor,\"})}),`\n`,(0,n.jsx)(e.span,{className:\"line\",children:(0,n.jsx)(e.span,{style:{color:\"#FFF4\"},children:\" *  selector: snapshot => ({ currentSelection: snapshot.editor.state.selection }),\"})}),`\n`,(0,n.jsx)(e.span,{className:\"line\",children:(0,n.jsx)(e.span,{style:{color:\"#FFF4\"},children:\" * })\"})}),`\n`,(0,n.jsx)(e.span,{className:\"line\",children:(0,n.jsx)(e.span,{style:{color:\"#FFF8\"},children:\" */\"})}),`\n`,(0,n.jsxs)(e.span,{className:\"line\",children:[(0,n.jsx)(e.span,{style:{color:\"#FFF8\"},children:\"export\"}),(0,n.jsx)(e.span,{style:{color:\"#FFF8\"},children:\" function\"}),(0,n.jsx)(e.span,{style:{color:\"#FFF\",fontWeight:\"bold\"},children:\" useEditorState\"}),(0,n.jsx)(e.span,{style:{color:\"#FFF8\"},children:\"<\"}),(0,n.jsx)(e.span,{style:{color:\"#FFF\",fontWeight:\"bold\"},children:\"TSelectorResult\"}),(0,n.jsx)(e.span,{style:{color:\"#FFF8\"},children:\">(\"})]}),`\n`,(0,n.jsxs)(e.span,{className:\"line\",children:[(0,n.jsx)(e.span,{style:{color:\"#FFF\"},children:\"  options\"}),(0,n.jsx)(e.span,{style:{color:\"#FFF8\"},children:\":\"}),(0,n.jsx)(e.span,{style:{color:\"#FFF\",fontWeight:\"bold\"},children:\" UseEditorStateOptions\"}),(0,n.jsx)(e.span,{style:{color:\"#FFF8\"},children:\"<\"}),(0,n.jsx)(e.span,{style:{color:\"#FFF\",fontWeight:\"bold\"},children:\"TSelectorResult\"}),(0,n.jsx)(e.span,{style:{color:\"#FFF8\"},children:\",\"}),(0,n.jsx)(e.span,{style:{color:\"#FFF\",fontWeight:\"bold\"},children:\" Editor\"}),(0,n.jsx)(e.span,{style:{color:\"#FFF8\"},children:\">\"}),(0,n.jsx)(e.span,{style:{color:\"#FFF8\"},children:\" |\"}),(0,n.jsx)(e.span,{style:{color:\"#FFF\",fontWeight:\"bold\"},children:\" UseEditorStateOptions\"}),(0,n.jsx)(e.span,{style:{color:\"#FFF8\"},children:\"<\"}),(0,n.jsx)(e.span,{style:{color:\"#FFF\",fontWeight:\"bold\"},children:\"TSelectorResult\"}),(0,n.jsx)(e.span,{style:{color:\"#FFF8\"},children:\",\"}),(0,n.jsx)(e.span,{style:{color:\"#FFF\",fontWeight:\"bold\"},children:\" Editor\"}),(0,n.jsx)(e.span,{style:{color:\"#FFF8\"},children:\" |\"}),(0,n.jsx)(e.span,{style:{color:\"#FFF\"},children:\" null\"}),(0,n.jsx)(e.span,{style:{color:\"#FFF8\"},children:\">,\"})]}),`\n`,(0,n.jsxs)(e.span,{className:\"line\",children:[(0,n.jsx)(e.span,{style:{color:\"#FFF8\"},children:\"):\"}),(0,n.jsx)(e.span,{style:{color:\"#FFF\",fontWeight:\"bold\"},children:\" TSelectorResult\"}),(0,n.jsx)(e.span,{style:{color:\"#FFF8\"},children:\" |\"}),(0,n.jsx)(e.span,{style:{color:\"#FFF\"},children:\" null \"}),(0,n.jsx)(e.span,{style:{color:\"#FFF8\"},children:\"{\"})]}),`\n`,(0,n.jsxs)(e.span,{className:\"line\",children:[(0,n.jsx)(e.span,{style:{color:\"#FFF8\"},children:\"  const\"}),(0,n.jsx)(e.span,{style:{color:\"#FFF8\"},children:\" [\"}),(0,n.jsx)(e.span,{style:{color:\"#FFF\"},children:\"editorStateManager\"}),(0,n.jsx)(e.span,{style:{color:\"#FFF8\"},children:\"]\"}),(0,n.jsx)(e.span,{style:{color:\"#FFF8\"},children:\" =\"}),(0,n.jsx)(e.span,{style:{color:\"#FFF\"},children:\" useState\"}),(0,n.jsx)(e.span,{style:{color:\"#FFF8\"},children:\"(()\"}),(0,n.jsx)(e.span,{style:{color:\"#FFF8\"},children:\" =>\"}),(0,n.jsx)(e.span,{style:{color:\"#FFF8\"},children:\" new\"}),(0,n.jsx)(e.span,{style:{color:\"#FFF\"},children:\" EditorStateManager\"}),(0,n.jsx)(e.span,{style:{color:\"#FFF8\"},children:\"(\"}),(0,n.jsx)(e.span,{style:{color:\"#FFF\"},children:\"options\"}),(0,n.jsx)(e.span,{style:{color:\"#FFF8\"},children:\".\"}),(0,n.jsx)(e.span,{style:{color:\"#FFF\"},children:\"editor\"}),(0,n.jsx)(e.span,{style:{color:\"#FFF8\"},children:\"))\"})]}),`\n`,(0,n.jsx)(e.span,{className:\"line\",children:\" \"}),`\n`,(0,n.jsxs)(e.span,{className:\"line\",children:[(0,n.jsx)(e.span,{style:{color:\"#FFF8\"},children:\"  //\"}),(0,n.jsx)(e.span,{style:{color:\"#FFF4\"},children:\" Using the `useSyncExternalStore` hook to sync the editor instance with the component state\"})]}),`\n`,(0,n.jsxs)(e.span,{className:\"line\",children:[(0,n.jsx)(e.span,{style:{color:\"#FFF8\"},children:\"  const\"}),(0,n.jsx)(e.span,{style:{color:\"#FFF\"},children:\" selectedState \"}),(0,n.jsx)(e.span,{style:{color:\"#FFF8\"},children:\"=\"}),(0,n.jsx)(e.span,{style:{color:\"#FFF\"},children:\" useSyncExternalStoreWithSelector\"}),(0,n.jsx)(e.span,{style:{color:\"#FFF8\"},children:\"(\"})]}),`\n`,(0,n.jsxs)(e.span,{className:\"line\",children:[(0,n.jsx)(e.span,{style:{color:\"#FFF\"},children:\"    editorStateManager\"}),(0,n.jsx)(e.span,{style:{color:\"#FFF8\"},children:\".\"}),(0,n.jsx)(e.span,{style:{color:\"#FFF\"},children:\"subscribe\"}),(0,n.jsx)(e.span,{style:{color:\"#FFF8\"},children:\",\"})]}),`\n`,(0,n.jsxs)(e.span,{className:\"line\",children:[(0,n.jsx)(e.span,{style:{color:\"#FFF\"},children:\"    editorStateManager\"}),(0,n.jsx)(e.span,{style:{color:\"#FFF8\"},children:\".\"}),(0,n.jsx)(e.span,{style:{color:\"#FFF\"},children:\"getSnapshot\"}),(0,n.jsx)(e.span,{style:{color:\"#FFF8\"},children:\",\"})]}),`\n`,(0,n.jsxs)(e.span,{className:\"line\",children:[(0,n.jsx)(e.span,{style:{color:\"#FFF\"},children:\"    editorStateManager\"}),(0,n.jsx)(e.span,{style:{color:\"#FFF8\"},children:\".\"}),(0,n.jsx)(e.span,{style:{color:\"#FFF\"},children:\"getServerSnapshot\"}),(0,n.jsx)(e.span,{style:{color:\"#FFF8\"},children:\",\"})]}),`\n`,(0,n.jsxs)(e.span,{className:\"line\",children:[(0,n.jsx)(e.span,{style:{color:\"#FFF\"},children:\"    options\"}),(0,n.jsx)(e.span,{style:{color:\"#FFF8\"},children:\".\"}),(0,n.jsx)(e.span,{style:{color:\"#FFF\"},children:\"selector \"}),(0,n.jsx)(e.span,{style:{color:\"#FFF8\"},children:\"as\"}),(0,n.jsx)(e.span,{style:{color:\"#FFF\",fontWeight:\"bold\"},children:\" UseEditorStateOptions\"}),(0,n.jsx)(e.span,{style:{color:\"#FFF8\"},children:\"<\"}),(0,n.jsx)(e.span,{style:{color:\"#FFF\",fontWeight:\"bold\"},children:\"TSelectorResult\"}),(0,n.jsx)(e.span,{style:{color:\"#FFF8\"},children:\",\"}),(0,n.jsx)(e.span,{style:{color:\"#FFF\",fontWeight:\"bold\"},children:\" Editor\"}),(0,n.jsx)(e.span,{style:{color:\"#FFF8\"},children:\" |\"}),(0,n.jsx)(e.span,{style:{color:\"#FFF\"},children:\" null\"}),(0,n.jsx)(e.span,{style:{color:\"#FFF8\"},children:\">[\"}),(0,n.jsx)(e.span,{style:{color:\"#FFF8\"},children:\"'selector'\"}),(0,n.jsx)(e.span,{style:{color:\"#FFF8\"},children:\"],\"})]}),`\n`,(0,n.jsxs)(e.span,{className:\"line\",children:[(0,n.jsx)(e.span,{style:{color:\"#FFF\"},children:\"    options\"}),(0,n.jsx)(e.span,{style:{color:\"#FFF8\"},children:\".\"}),(0,n.jsx)(e.span,{style:{color:\"#FFF\"},children:\"equalityFn \"}),(0,n.jsx)(e.span,{style:{color:\"#FFF8\"},children:\"??\"}),(0,n.jsx)(e.span,{style:{color:\"#FFF\"},children:\" deepEqual\"}),(0,n.jsx)(e.span,{style:{color:\"#FFF8\"},children:\",\"})]}),`\n`,(0,n.jsx)(e.span,{className:\"line\",children:(0,n.jsx)(e.span,{style:{color:\"#FFF8\"},children:\"  )\"})}),`\n`,(0,n.jsx)(e.span,{className:\"line\",children:\" \"}),`\n`,(0,n.jsxs)(e.span,{className:\"line\",children:[(0,n.jsx)(e.span,{style:{color:\"#FFF\"},children:\"  useIsomorphicLayoutEffect\"}),(0,n.jsx)(e.span,{style:{color:\"#FFF8\"},children:\"(()\"}),(0,n.jsx)(e.span,{style:{color:\"#FFF8\"},children:\" =>\"}),(0,n.jsx)(e.span,{style:{color:\"#FFF8\"},children:\" {\"})]}),`\n`,(0,n.jsxs)(e.span,{className:\"line\",children:[(0,n.jsx)(e.span,{style:{color:\"#FFF8\"},children:\"    return\"}),(0,n.jsx)(e.span,{style:{color:\"#FFF\"},children:\" editorStateManager\"}),(0,n.jsx)(e.span,{style:{color:\"#FFF8\"},children:\".\"}),(0,n.jsx)(e.span,{style:{color:\"#FFF\"},children:\"watch\"}),(0,n.jsx)(e.span,{style:{color:\"#FFF8\"},children:\"(\"}),(0,n.jsx)(e.span,{style:{color:\"#FFF\"},children:\"options\"}),(0,n.jsx)(e.span,{style:{color:\"#FFF8\"},children:\".\"}),(0,n.jsx)(e.span,{style:{color:\"#FFF\"},children:\"editor\"}),(0,n.jsx)(e.span,{style:{color:\"#FFF8\"},children:\")\"})]}),`\n`,(0,n.jsxs)(e.span,{className:\"line\",children:[(0,n.jsx)(e.span,{style:{color:\"#FFF8\"},children:\"  },\"}),(0,n.jsx)(e.span,{style:{color:\"#FFF8\"},children:\" [\"}),(0,n.jsx)(e.span,{style:{color:\"#FFF\"},children:\"options\"}),(0,n.jsx)(e.span,{style:{color:\"#FFF8\"},children:\".\"}),(0,n.jsx)(e.span,{style:{color:\"#FFF\"},children:\"editor\"}),(0,n.jsx)(e.span,{style:{color:\"#FFF8\"},children:\",\"}),(0,n.jsx)(e.span,{style:{color:\"#FFF\"},children:\" editorStateManager\"}),(0,n.jsx)(e.span,{style:{color:\"#FFF8\"},children:\"])\"})]}),`\n`,(0,n.jsx)(e.span,{className:\"line\",children:\" \"}),`\n`,(0,n.jsxs)(e.span,{className:\"line\",children:[(0,n.jsx)(e.span,{style:{color:\"#FFF\"},children:\"  useDebugValue\"}),(0,n.jsx)(e.span,{style:{color:\"#FFF8\"},children:\"(\"}),(0,n.jsx)(e.span,{style:{color:\"#FFF\"},children:\"selectedState\"}),(0,n.jsx)(e.span,{style:{color:\"#FFF8\"},children:\")\"})]}),`\n`,(0,n.jsx)(e.span,{className:\"line\",children:\" \"}),`\n`,(0,n.jsxs)(e.span,{className:\"line\",children:[(0,n.jsx)(e.span,{style:{color:\"#FFF8\"},children:\"  return\"}),(0,n.jsx)(e.span,{style:{color:\"#FFF\"},children:\" selectedState\"})]}),`\n`,(0,n.jsx)(e.span,{className:\"line\",children:(0,n.jsx)(e.span,{style:{color:\"#FFF8\"},children:\"}\"})})]})})}),`\n`,(0,n.jsxs)(e.blockquote,{children:[`\n`,(0,n.jsxs)(e.p,{children:[\"Using the \",(0,n.jsx)(e.code,{children:\"useSyncExternalStore\"}),\" hook to sync the editor instance with the component state\"]}),`\n`]}),`\n`,(0,n.jsxs)(e.p,{children:[\"In the \",(0,n.jsx)(e.code,{children:\"EditorContent.tsx\"}),\", the import was from \",(0,n.jsx)(e.code,{children:\"use-sync-external-store/shim\"}),\" but here in this useEditorState, import is from \",(0,n.jsx)(e.code,{children:\"use-sync-external-store/shim/with-selector\"}),\".\"]}),`\n`,(0,n.jsx)(e.h3,{id:\"useeditorts\",children:\"useEditor.ts\"}),`\n`,(0,n.jsx)(e.div,{\"data-rehype-pretty-code-fragment\":\"\",children:(0,n.jsx)(e.pre,{\"data-language\":\"js\",\"data-theme\":\"default\",children:(0,n.jsxs)(e.code,{\"data-language\":\"js\",\"data-theme\":\"default\",children:[(0,n.jsxs)(e.span,{className:\"line\",children:[(0,n.jsx)(e.span,{style:{color:\"#FFF8\"},children:\"import\"}),(0,n.jsx)(e.span,{style:{color:\"#FFF8\"},children:\" {\"}),(0,n.jsx)(e.span,{style:{color:\"#FFF\"},children:\" useSyncExternalStore \"}),(0,n.jsx)(e.span,{style:{color:\"#FFF8\"},children:\"}\"}),(0,n.jsx)(e.span,{style:{color:\"#FFF8\"},children:\" from\"}),(0,n.jsx)(e.span,{style:{color:\"#FFF8\"},children:\" 'use-sync-external-store/shim'\"})]}),`\n`,(0,n.jsx)(e.span,{className:\"line\",children:(0,n.jsx)(e.span,{style:{color:\"#FFF8\"},children:\"...\"})}),`\n`,(0,n.jsxs)(e.span,{className:\"line\",children:[(0,n.jsx)(e.span,{style:{color:\"#FFF8\"},children:\"export\"}),(0,n.jsx)(e.span,{style:{color:\"#FFF8\"},children:\" function\"}),(0,n.jsx)(e.span,{style:{color:\"#FFF\",fontWeight:\"bold\"},children:\" useEditor\"}),(0,n.jsx)(e.span,{style:{color:\"#FFF8\"},children:\"(\"})]}),`\n`,(0,n.jsxs)(e.span,{className:\"line\",children:[(0,n.jsx)(e.span,{style:{color:\"#FFF\"},children:\"  options\"}),(0,n.jsx)(e.span,{style:{color:\"#FFF8\"},children:\":\"}),(0,n.jsx)(e.span,{style:{color:\"#FFF\",fontWeight:\"bold\"},children:\" UseEditorOptions\"}),(0,n.jsx)(e.span,{style:{color:\"#FFF8\"},children:\" =\"}),(0,n.jsx)(e.span,{style:{color:\"#FFF8\"},children:\" {},\"})]}),`\n`,(0,n.jsxs)(e.span,{className:\"line\",children:[(0,n.jsx)(e.span,{style:{color:\"#FFF\"},children:\"  deps\"}),(0,n.jsx)(e.span,{style:{color:\"#FFF8\"},children:\":\"}),(0,n.jsx)(e.span,{style:{color:\"#FFF\",fontWeight:\"bold\"},children:\" DependencyList\"}),(0,n.jsx)(e.span,{style:{color:\"#FFF8\"},children:\" =\"}),(0,n.jsx)(e.span,{style:{color:\"#FFF8\"},children:\" [],\"})]}),`\n`,(0,n.jsxs)(e.span,{className:\"line\",children:[(0,n.jsx)(e.span,{style:{color:\"#FFF8\"},children:\"):\"}),(0,n.jsx)(e.span,{style:{color:\"#FFF\",fontWeight:\"bold\"},children:\" Editor\"}),(0,n.jsx)(e.span,{style:{color:\"#FFF8\"},children:\" |\"}),(0,n.jsx)(e.span,{style:{color:\"#FFF\"},children:\" null \"}),(0,n.jsx)(e.span,{style:{color:\"#FFF8\"},children:\"{\"})]}),`\n`,(0,n.jsxs)(e.span,{className:\"line\",children:[(0,n.jsx)(e.span,{style:{color:\"#FFF8\"},children:\"  const\"}),(0,n.jsx)(e.span,{style:{color:\"#FFF\"},children:\" mostRecentOptions \"}),(0,n.jsx)(e.span,{style:{color:\"#FFF8\"},children:\"=\"}),(0,n.jsx)(e.span,{style:{color:\"#FFF\"},children:\" useRef\"}),(0,n.jsx)(e.span,{style:{color:\"#FFF8\"},children:\"(\"}),(0,n.jsx)(e.span,{style:{color:\"#FFF\"},children:\"options\"}),(0,n.jsx)(e.span,{style:{color:\"#FFF8\"},children:\")\"})]}),`\n`,(0,n.jsx)(e.span,{className:\"line\",children:\" \"}),`\n`,(0,n.jsxs)(e.span,{className:\"line\",children:[(0,n.jsx)(e.span,{style:{color:\"#FFF\"},children:\"  mostRecentOptions\"}),(0,n.jsx)(e.span,{style:{color:\"#FFF8\"},children:\".\"}),(0,n.jsx)(e.span,{style:{color:\"#FFF\"},children:\"current \"}),(0,n.jsx)(e.span,{style:{color:\"#FFF8\"},children:\"=\"}),(0,n.jsx)(e.span,{style:{color:\"#FFF\"},children:\" options\"})]}),`\n`,(0,n.jsx)(e.span,{className:\"line\",children:\" \"}),`\n`,(0,n.jsxs)(e.span,{className:\"line\",children:[(0,n.jsx)(e.span,{style:{color:\"#FFF8\"},children:\"  const\"}),(0,n.jsx)(e.span,{style:{color:\"#FFF8\"},children:\" [\"}),(0,n.jsx)(e.span,{style:{color:\"#FFF\"},children:\"instanceManager\"}),(0,n.jsx)(e.span,{style:{color:\"#FFF8\"},children:\"]\"}),(0,n.jsx)(e.span,{style:{color:\"#FFF8\"},children:\" =\"}),(0,n.jsx)(e.span,{style:{color:\"#FFF\"},children:\" useState\"}),(0,n.jsx)(e.span,{style:{color:\"#FFF8\"},children:\"(()\"}),(0,n.jsx)(e.span,{style:{color:\"#FFF8\"},children:\" =>\"}),(0,n.jsx)(e.span,{style:{color:\"#FFF8\"},children:\" new\"}),(0,n.jsx)(e.span,{style:{color:\"#FFF\"},children:\" EditorInstanceManager\"}),(0,n.jsx)(e.span,{style:{color:\"#FFF8\"},children:\"(\"}),(0,n.jsx)(e.span,{style:{color:\"#FFF\"},children:\"mostRecentOptions\"}),(0,n.jsx)(e.span,{style:{color:\"#FFF8\"},children:\"))\"})]}),`\n`,(0,n.jsx)(e.span,{className:\"line\",children:\" \"}),`\n`,(0,n.jsxs)(e.span,{className:\"line\",children:[(0,n.jsx)(e.span,{style:{color:\"#FFF8\"},children:\"  const\"}),(0,n.jsx)(e.span,{style:{color:\"#FFF\"},children:\" editor \"}),(0,n.jsx)(e.span,{style:{color:\"#FFF8\"},children:\"=\"}),(0,n.jsx)(e.span,{style:{color:\"#FFF\"},children:\" useSyncExternalStore\"}),(0,n.jsx)(e.span,{style:{color:\"#FFF8\"},children:\"(\"})]}),`\n`,(0,n.jsxs)(e.span,{className:\"line\",children:[(0,n.jsx)(e.span,{style:{color:\"#FFF\"},children:\"    instanceManager\"}),(0,n.jsx)(e.span,{style:{color:\"#FFF8\"},children:\".\"}),(0,n.jsx)(e.span,{style:{color:\"#FFF\"},children:\"subscribe\"}),(0,n.jsx)(e.span,{style:{color:\"#FFF8\"},children:\",\"})]}),`\n`,(0,n.jsxs)(e.span,{className:\"line\",children:[(0,n.jsx)(e.span,{style:{color:\"#FFF\"},children:\"    instanceManager\"}),(0,n.jsx)(e.span,{style:{color:\"#FFF8\"},children:\".\"}),(0,n.jsx)(e.span,{style:{color:\"#FFF\"},children:\"getEditor\"}),(0,n.jsx)(e.span,{style:{color:\"#FFF8\"},children:\",\"})]}),`\n`,(0,n.jsxs)(e.span,{className:\"line\",children:[(0,n.jsx)(e.span,{style:{color:\"#FFF\"},children:\"    instanceManager\"}),(0,n.jsx)(e.span,{style:{color:\"#FFF8\"},children:\".\"}),(0,n.jsx)(e.span,{style:{color:\"#FFF\"},children:\"getServerSnapshot\"}),(0,n.jsx)(e.span,{style:{color:\"#FFF8\"},children:\",\"})]}),`\n`,(0,n.jsx)(e.span,{className:\"line\",children:(0,n.jsx)(e.span,{style:{color:\"#FFF8\"},children:\"  )\"})}),`\n`,(0,n.jsx)(e.span,{className:\"line\",children:\" \"}),`\n`,(0,n.jsxs)(e.span,{className:\"line\",children:[(0,n.jsx)(e.span,{style:{color:\"#FFF\"},children:\"  useDebugValue\"}),(0,n.jsx)(e.span,{style:{color:\"#FFF8\"},children:\"(\"}),(0,n.jsx)(e.span,{style:{color:\"#FFF\"},children:\"editor\"}),(0,n.jsx)(e.span,{style:{color:\"#FFF8\"},children:\")\"})]})]})})}),`\n`,(0,n.jsx)(e.p,{children:\"Here the external store is instanceManager.\"}),`\n`,(0,n.jsx)(e.h3,{id:\"about-me\",children:\"About me:\"}),`\n`,(0,n.jsx)(e.p,{children:\"Hey, my name is Ramu Narasinga. I study large open-source projects and create content about their codebase architecture and best practices, sharing it through articles, videos.\"}),`\n`,(0,n.jsx)(e.p,{children:(0,n.jsx)(e.em,{children:(0,n.jsxs)(e.strong,{children:[\"I am open to work on interesting projects. Send me an email at \",(0,n.jsx)(e.a,{href:\"mailto:ramu.narasinga@gmail.com\",children:\"ramu.narasinga@gmail.com\"})]})})}),`\n`,(0,n.jsxs)(e.p,{children:[\"My Github\\u200A\\u2014\\u200A\",(0,n.jsx)(e.a,{href:\"https://github.com/ramu-narasinga\",children:\"https://github.com/ramu-narasinga\"})]}),`\n`,(0,n.jsxs)(e.p,{children:[\"My website\\u200A\\u2014\\u200A\",(0,n.jsx)(e.a,{href:\"https://ramunarasinga.com/\",children:\"https://ramunarasinga.com\"})]}),`\n`,(0,n.jsxs)(e.p,{children:[\"My Youtube channel\\u200A\\u2014\\u200A\",(0,n.jsx)(e.a,{href:\"https://www.youtube.com/@thinkthroo\",children:\"https://www.youtube.com/@thinkthroo\"})]}),`\n`,(0,n.jsxs)(e.p,{children:[\"Learning platform\\u200A\\u2014\\u200A\",(0,n.jsx)(e.a,{href:\"https://thinkthroo.com/\",children:\"https://thinkthroo.com\"})]}),`\n`,(0,n.jsxs)(e.p,{children:[\"Codebase Architecture\\u200A\\u2014\\u200A\",(0,n.jsx)(e.a,{href:\"https://app.thinkthroo.com/architecture\",children:\"https://app.thinkthroo.com/architecture\"})]}),`\n`,(0,n.jsxs)(e.p,{children:[\"Best practices\\u200A\\u2014\\u200A\",(0,n.jsx)(e.a,{href:\"https://app.thinkthroo.com/best-practices\",children:\"https://app.thinkthroo.com/best-practices\"})]}),`\n`,(0,n.jsxs)(e.p,{children:[\"Production-grade projects\\u200A\\u2014\\u200A\",(0,n.jsx)(e.a,{href:\"https://app.thinkthroo.com/production-grade-projects\",children:\"https://app.thinkthroo.com/production-grade-projects\"})]}),`\n`,(0,n.jsx)(e.h3,{id:\"references\",children:\"References:\"}),`\n`,(0,n.jsxs)(e.ol,{children:[`\n`,(0,n.jsxs)(e.li,{children:[`\n`,(0,n.jsx)(e.p,{children:(0,n.jsx)(e.a,{href:\"https://github.com/search?q=repo%3Aueberdosis%2Ftiptap%20useSyncExternalStore&type=code\",children:\"useSyncExternalStore&type=code\"})}),`\n`]}),`\n`,(0,n.jsxs)(e.li,{children:[`\n`,(0,n.jsx)(e.p,{children:(0,n.jsx)(e.a,{href:\"https://github.com/ueberdosis/tiptap/blob/4d9cc0519f7d4d3df69cd2d6839718a9ac92244c/packages/react/src/EditorContent.tsx#L32\",children:\"packages/react/src/EditorContent.tsx#L32\"})}),`\n`]}),`\n`,(0,n.jsxs)(e.li,{children:[`\n`,(0,n.jsx)(e.p,{children:(0,n.jsx)(e.a,{href:\"https://github.com/ueberdosis/tiptap/blob/4d9cc0519f7d4d3df69cd2d6839718a9ac92244c/packages/react/src/useEditorState.ts#L162\",children:\"packages/react/src/useEditorState.ts#L162\"})}),`\n`]}),`\n`,(0,n.jsxs)(e.li,{children:[`\n`,(0,n.jsx)(e.p,{children:(0,n.jsx)(e.a,{href:\"https://github.com/ueberdosis/tiptap/blob/4d9cc0519f7d4d3df69cd2d6839718a9ac92244c/packages/react/src/useEditor.ts#L345\",children:\"packages/react/src/useEditor.ts#L345\"})}),`\n`]}),`\n`,(0,n.jsxs)(e.li,{children:[`\n`,(0,n.jsx)(e.p,{children:(0,n.jsx)(e.a,{href:\"https://react.dev/reference/react/useSyncExternalStore\",children:\"https://react.dev/reference/react/useSyncExternalStore\"})}),`\n`]}),`\n`]})]})}function d(l={}){let{wrapper:e}=l.components||{};return e?(0,n.jsx)(e,{...l,children:(0,n.jsx)(i,{...l})}):i(l)}return b(E);})();\n;return Component;"
  },
  "_id": "blog/usesyncexternalstore-in-tiptap.mdx",
  "_raw": {
    "sourceFilePath": "blog/usesyncexternalstore-in-tiptap.mdx",
    "sourceFileName": "usesyncexternalstore-in-tiptap.mdx",
    "sourceFileDir": "blog",
    "contentType": "mdx",
    "flattenedPath": "blog/usesyncexternalstore-in-tiptap"
  },
  "type": "Doc",
  "slug": "/blog/usesyncexternalstore-in-tiptap",
  "slugAsParams": "usesyncexternalstore-in-tiptap"
}